setup.py
netpenguins_roadtx.egg-info/PKG-INFO
netpenguins_roadtx.egg-info/SOURCES.txt
netpenguins_roadtx.egg-info/dependency_links.txt
netpenguins_roadtx.egg-info/entry_points.txt
netpenguins_roadtx.egg-info/not-zip-safe
netpenguins_roadtx.egg-info/requires.txt
netpenguins_roadtx.egg-info/top_level.txt
roadtools/roadtx/federation.py
roadtools/roadtx/firstpartyscopes.json
roadtools/roadtx/keepass.py
roadtools/roadtx/main.py
roadtools/roadtx/selenium.py