Metadata-Version: 2.1
Name: netpenguins-roadtx
Version: 1.10.0
Summary: ROADtools Token eXchange
Home-page: https://github.com/dirkjanm/ROADtools/
Author: Dirk-jan Mollema
Author-email: dirkjan@outsidersecurity.nl
License: MIT
Classifier: Intended Audience :: Information Technology
Classifier: License :: OSI Approved :: MIT License
Classifier: Programming Language :: Python :: 3
Classifier: Programming Language :: Python :: 3.7
Classifier: Programming Language :: Python :: 3.8
Classifier: Programming Language :: Python :: 3.9
Classifier: Programming Language :: Python :: 3.10
Requires-Dist: roadlib>=0.27
Requires-Dist: requests
Requires-Dist: selenium
Requires-Dist: selenium-wire
Requires-Dist: pyotp
Requires-Dist: pycryptodomex
Requires-Dist: signxml
Requires-Dist: blinker<1.8.0
